udi/__init__.py
udi/constants.py
udi/core.py
udi/exception.py
udi/flows.py
udi/rest_client.py
udi/simple_flow.py
udi/utils.py
udi/models/__init__.py
udi/models/pipeline_model.py
ibm_udi-1.0.1.dist-info/METADATA
ibm_udi-1.0.1.dist-info/WHEEL
ibm_udi-1.0.1.dist-info/top_level.txt
ibm_udi-1.0.1.dist-info/RECORD
