Metadata-Version: 2.4
Name: ibm-udi
Version: 1.0.1
Summary: IBM UDI SDK.
Author-email: Afiz <afizshaik@in.ibm.com>, Aditya <adityars@ibm.com>, Pragathi <pragathi.prashanth@ibm.com>
License-Expression: Apache-2.0
Project-URL: Homepage, https://github.ibm.com/wdp-gov/datasift-sdk
Classifier: Programming Language :: Python :: 3
Classifier: Operating System :: OS Independent
Requires-Python: >=3.11
Requires-Dist: requests>=2.32.3
